{"noiseKey":{"private":{"type":"Buffer","data":"IPU/pN/BQJSvqMeIaxAhh70GrtktVDjzZGl6Z/wvwlY="},"public":{"type":"Buffer","data":"qrhlAp8l3LqBSQbt5o/7V0ZtUJZT+Y491s2maN/uTiY="}},"pairingEphemeralKeyPair":{"private":{"type":"Buffer","data":"mAuVpgkrtadtbrLm5UYg/gpcQB8yGVNDYtsX75mcQFI="},"public":{"type":"Buffer","data":"vQXIh/pqfoY9fl5g/7tWjszjFNQQfB5U7G5UUhaKh2I="}},"signedIdentityKey":{"private":{"type":"Buffer","data":"MMKc0/sl7TyBCMi1uWo2NvvinmV1S1kFmRinDKK+O3U="},"public":{"type":"Buffer","data":"KqxN5Y6DUbUKkbNFB5CtNtxE8wOhM/nbkFMJhkFp4lk="}},"signedPreKey":{"keyPair":{"private":{"type":"Buffer","data":"QIKt1SntD2otM/rDJ2Sx6iyFXfbQwgSPxVlWWYH0Kmg="},"public":{"type":"Buffer","data":"uHm8bo4tAOmq2QjBV+oWfzkvsHPqnw2clBFz+TTXShA="}},"signature":{"type":"Buffer","data":"ubHBvsHy8FA/Wg+DHlp32uX+HeFK06CpjSb1DQODVs0lROzuNP0Hr3Xem9cwb5zqC+cP9FqZZoZNKGXmITzyjg=="},"keyId":1},"registrationId":40,"advSecretKey":"bwzLkxx/vuFLhOLDsCQ00JxS6VatwEnagEheksuHEx8=","processedHistoryMessages":[{"key":{"remoteJid":"6283841167449@s.whatsapp.net","fromMe":true,"id":"AD4E2DA5D4DD8E257C282B1F22F336C5"},"messageTimestamp":1734615567},{"key":{"remoteJid":"6283841167449@s.whatsapp.net","fromMe":true,"id":"2687626646AD67EA13B6604A68F5DBC0"},"messageTimestamp":1734615568},{"key":{"remoteJid":"6283841167449@s.whatsapp.net","fromMe":true,"id":"E5BF6F44C530DCE3D8B0820C42FA8F60"},"messageTimestamp":1734615587},{"key":{"remoteJid":"6283841167449@s.whatsapp.net","fromMe":true,"id":"B12EEC7C7836CD57864D44F49112AA59"},"messageTimestamp":1734615595},{"key":{"remoteJid":"6283841167449@s.whatsapp.net","fromMe":true,"id":"DAA85A6F5C02B11E52E5CC1F4B6660E0"},"messageTimestamp":1734615597},{"key":{"remoteJid":"6283841167449@s.whatsapp.net","fromMe":true,"id":"27457E0A7B2A237754714E9A56A64A16"},"messageTimestamp":1734615599},{"key":{"remoteJid":"6283841167449@s.whatsapp.net","fromMe":true,"id":"B3A50019B402314E670355A9E5F02EC7"},"messageTimestamp":1734615602},{"key":{"remoteJid":"6283841167449@s.whatsapp.net","fromMe":true,"id":"32EF4377515A3A9DBB453DE8E0C420B7"},"messageTimestamp":1734615605},{"key":{"remoteJid":"6283841167449@s.whatsapp.net","fromMe":true,"id":"67C57EFA79AD47E4E690A1C335DE4DE5"},"messageTimestamp":1734615606},{"key":{"remoteJid":"6283841167449@s.whatsapp.net","fromMe":true,"id":"A4E67C698A7228DD52DB11BE26CEB101"},"messageTimestamp":1734615613},{"key":{"remoteJid":"6283841167449@s.whatsapp.net","fromMe":true,"id":"6C94C07C3C2F7F6A999728E0D25AD720"},"messageTimestamp":1734615615},{"key":{"remoteJid":"6283841167449@s.whatsapp.net","fromMe":true,"id":"1D94716037A4C5D99A5151EE4C627057"},"messageTimestamp":1734615617},{"key":{"remoteJid":"6283841167449@s.whatsapp.net","fromMe":true,"id":"C7730C7C13B2F1A9FFD11BB5A60EDCAF"},"messageTimestamp":1734615622},{"key":{"remoteJid":"6283841167449@s.whatsapp.net","fromMe":true,"id":"AD36AB2966FF6CA0BBB6847053E83C92"},"messageTimestamp":1734615625},{"key":{"remoteJid":"6283841167449@s.whatsapp.net","fromMe":true,"id":"721FDFF5B354B7840C9F2FA8A7B9A969"},"messageTimestamp":1734615630},{"key":{"remoteJid":"6283841167449@s.whatsapp.net","fromMe":true,"id":"98D939C9B986D648D978AF90CDA50ACB"},"messageTimestamp":1734615638},{"key":{"remoteJid":"6283841167449@s.whatsapp.net","fromMe":true,"id":"1DDF49352B1D5D3B83C6DD53348D67DA"},"messageTimestamp":1734615645},{"key":{"remoteJid":"6283841167449@s.whatsapp.net","fromMe":true,"id":"FE57D379231B030C1505AE34FCB7D79D"},"messageTimestamp":1734615647},{"key":{"remoteJid":"6283841167449@s.whatsapp.net","fromMe":true,"id":"5697B3843AA55276929B16BC9DD16D1D"},"messageTimestamp":1734615651}],"nextPreKeyId":62,"firstUnuploadedPreKeyId":62,"accountSyncCounter":1,"accountSettings":{"unarchiveChats":false},"registered":true,"pairingCode":"47D4VZQ4","me":{"id":"6283841167449:20@s.whatsapp.net","lid":"6644398293242:20@lid","name":"AyamGoreng🪿"},"account":{"details":"CLG+l6EFEIbEkLsGGA0gACgA","accountSignatureKey":"9JZoM9BnOIkwkqY4qybqhEBYP3zhn78t2ZW8jgAIaGY=","accountSignature":"fkEWAUpnJhzCSedh81LBOBAGGQFeTrjyP/YB5UZhFP9ZTzyeDU2BSX553tKmpwJP+0CCJxQS8iwourbuz13nBw==","deviceSignature":"5K/TNTsZKUVNKQSK3HmMsXXVAiAuewjBSkCXhcKl0MfEZGWziNc8cDseyANjm3HDgU0cqjeQVa8ZXGYkRpc9iw=="},"signalIdentities":[{"identifier":{"name":"6283841167449:20@s.whatsapp.net","deviceId":0},"identifierKey":{"type":"Buffer","data":"BfSWaDPQZziJMJKmOKsm6oRAWD984Z+/LdmVvI4ACGhm"}}],"platform":"android","routingInfo":{"type":"Buffer","data":"CBIICA=="},"lastAccountSyncTimestamp":1734616063,"lastPropHash":"TrDC9","myAppStateKeyId":"AAAAAFcf"}